k8syaml/__init__.py
k8syaml/encode_base64.py
k8syaml/k8s_yaml_obj.py
k8syaml-0.1.2.dist-info/LICENSE
k8syaml-0.1.2.dist-info/METADATA
k8syaml-0.1.2.dist-info/WHEEL
k8syaml-0.1.2.dist-info/top_level.txt
k8syaml-0.1.2.dist-info/RECORD
