Metadata-Version: 2.1
Name: k8syaml
Version: 0.1.2
Summary: Programmatic generation of yaml files for K8s' objects
Home-page: https://github.com/paoloalba/deployer_k8s
Author: Paolo Alba
Author-email: paoloalbag@gmail.com
License: UNKNOWN
Platform: UNKNOWN
Classifier: Programming Language :: Python :: 3
Classifier: License :: OSI Approved :: MIT License
Classifier: Operating System :: OS Independent
Requires-Python: >=3.6
